{
  "message": "Data getted successfully",
  "data": [
    {
      "id": 7,
      "name": "Saturday",
      "limits": [
        {
          "hour": 0,
          "functionalStation": [
            { "functionalStationId": "1", "limit": 1000 },
            { "functionalStationId": "2", "limit": 2000 }
          ]
        },
        {
          "hour": 1,
          "functionalStation": [
            { "functionalStationId": "1", "limit": 1100 },
            { "functionalStationId": "2", "limit": 2000 }
          ]
        },
        {
          "hour": 2,
          "functionalStation": [
            { "functionalStationId": "1", "limit": 1200 },
            { "functionalStationId": "2", "limit": 2000 }
          ]
        },
        {
          "hour": 3,
          "functionalStation": [
            { "functionalStationId": "1", "limit": 1300 },
            { "functionalStationId": "2", "limit": 2000 }
          ]
        },
        {
          "hour": 4,
          "functionalStation": [
            { "functionalStationId": "1", "limit": 1400 },
            { "functionalStationId": "2", "limit": 2000 }
          ]
        },
        {
          "hour": 5,
          "functionalStation": [
            { "functionalStationId": "1", "limit": 1500 },
            { "functionalStationId": "2", "limit": 2000 }
          ]
        },
        {
          "hour": 6,
          "functionalStation": [
            { "functionalStationId": "1", "limit": 1600 },
            { "functionalStationId": "2", "limit": 2000 }
          ]
        },
        {
          "hour": 7,
          "functionalStation": [
            { "functionalStationId": "1", "limit": 1700 },
            { "functionalStationId": "2", "limit": 2000 }
          ]
        },
        {
          "hour": 8,
          "functionalStation": [
            { "functionalStationId": "1", "limit": 1800 },
            { "functionalStationId": "2", "limit": 2000 }
          ]
        },
        {
          "hour": 9,
          "functionalStation": [
            { "functionalStationId": "1", "limit": 1900 },
            { "functionalStationId": "2", "limit": 2000 }
          ]
        },
        {
          "hour": 10,
          "functionalStation": [
            { "functionalStationId": "1", "limit": 2000 },
            { "functionalStationId": "2", "limit": 2000 }
          ]
        },
        {
          "hour": 11,
          "functionalStation": [
            { "functionalStationId": "1", "limit": 1100 },
            { "functionalStationId": "2", "limit": 2000 }
          ]
        },
        {
          "hour": 12,
          "functionalStation": [
            { "functionalStationId": "1", "limit": 1200 },
            { "functionalStationId": "2", "limit": 2000 }
          ]
        },
        {
          "hour": 13,
          "functionalStation": [
            { "functionalStationId": "1", "limit": 1300 },
            { "functionalStationId": "2", "limit": 2000 }
          ]
        },
        {
          "hour": 14,
          "functionalStation": [
            { "functionalStationId": "1", "limit": 1400 },
            { "functionalStationId": "2", "limit": 2000 }
          ]
        },
        {
          "hour": 15,
          "functionalStation": [
            { "functionalStationId": "1", "limit": 1500 },
            { "functionalStationId": "2", "limit": 2000 }
          ]
        },
        {
          "hour": 16,
          "functionalStation": [
            { "functionalStationId": "1", "limit": 2600 },
            { "functionalStationId": "2", "limit": 2000 }
          ]
        },
        {
          "hour": 17,
          "functionalStation": [
            { "functionalStationId": "1", "limit": 2700 },
            { "functionalStationId": "2", "limit": 2000 }
          ]
        },
        {
          "hour": 18,
          "functionalStation": [
            { "functionalStationId": "1", "limit": 2800 },
            { "functionalStationId": "2", "limit": 2000 }
          ]
        },
        {
          "hour": 19,
          "functionalStation": [
            { "functionalStationId": "1", "limit": 1900 },
            { "functionalStationId": "2", "limit": 2000 }
          ]
        },
        {
          "hour": 20,
          "functionalStation": [
            { "functionalStationId": "1", "limit": 3000 },
            { "functionalStationId": "2", "limit": 2000 }
          ]
        },
        {
          "hour": 21,
          "functionalStation": [
            { "functionalStationId": "1", "limit": 3100 },
            { "functionalStationId": "2", "limit": 2000 }
          ]
        },
        {
          "hour": 22,
          "functionalStation": [
            { "functionalStationId": "1", "limit": 3200 },
            { "functionalStationId": "2", "limit": 2000 }
          ]
        },
        {
          "hour": 23,
          "functionalStation": [
            { "functionalStationId": "1", "limit": 3300 },
            { "functionalStationId": "2", "limit": 2000 }
          ]
        }
      ]
    },
    {
      "id": 3,
      "name": "Tuesday",
      "limits": [
        {
          "hour": 0,
          "functionalStation": [
            { "functionalStationId": "1", "limit": 1000 },
            { "functionalStationId": "2", "limit": 2000 }
          ]
        },
        {
          "hour": 1,
          "functionalStation": [
            { "functionalStationId": "1", "limit": 1100 },
            { "functionalStationId": "2", "limit": 2000 }
          ]
        },
        {
          "hour": 2,
          "functionalStation": [
            { "functionalStationId": "1", "limit": 1200 },
            { "functionalStationId": "2", "limit": 2000 }
          ]
        },
        {
          "hour": 3,
          "functionalStation": [
            { "functionalStationId": "1", "limit": 1300 },
            { "functionalStationId": "2", "limit": 2000 }
          ]
        },
        {
          "hour": 4,
          "functionalStation": [
            { "functionalStationId": "1", "limit": 1400 },
            { "functionalStationId": "2", "limit": 2000 }
          ]
        },
        {
          "hour": 5,
          "functionalStation": [
            { "functionalStationId": "1", "limit": 1500 },
            { "functionalStationId": "2", "limit": 2000 }
          ]
        },
        {
          "hour": 6,
          "functionalStation": [
            { "functionalStationId": "1", "limit": 1600 },
            { "functionalStationId": "2", "limit": 2000 }
          ]
        },
        {
          "hour": 7,
          "functionalStation": [
            { "functionalStationId": "1", "limit": 1700 },
            { "functionalStationId": "2", "limit": 2000 }
          ]
        },
        {
          "hour": 8,
          "functionalStation": [
            { "functionalStationId": "1", "limit": 1800 },
            { "functionalStationId": "2", "limit": 2000 }
          ]
        },
        {
          "hour": 9,
          "functionalStation": [
            { "functionalStationId": "1", "limit": 1900 },
            { "functionalStationId": "2", "limit": 2000 }
          ]
        },
        {
          "hour": 10,
          "functionalStation": [
            { "functionalStationId": "1", "limit": 2000 },
            { "functionalStationId": "2", "limit": 2000 }
          ]
        },
        {
          "hour": 11,
          "functionalStation": [
            { "functionalStationId": "1", "limit": 1100 },
            { "functionalStationId": "2", "limit": 2000 }
          ]
        },
        {
          "hour": 12,
          "functionalStation": [
            { "functionalStationId": "1", "limit": 1200 },
            { "functionalStationId": "2", "limit": 2000 }
          ]
        },
        {
          "hour": 13,
          "functionalStation": [
            { "functionalStationId": "1", "limit": 1300 },
            { "functionalStationId": "2", "limit": 2000 }
          ]
        },
        {
          "hour": 14,
          "functionalStation": [
            { "functionalStationId": "1", "limit": 1400 },
            { "functionalStationId": "2", "limit": 2000 }
          ]
        },
        {
          "hour": 15,
          "functionalStation": [
            { "functionalStationId": "1", "limit": 1500 },
            { "functionalStationId": "2", "limit": 2000 }
          ]
        },
        {
          "hour": 16,
          "functionalStation": [
            { "functionalStationId": "1", "limit": 2600 },
            { "functionalStationId": "2", "limit": 2000 }
          ]
        },
        {
          "hour": 17,
          "functionalStation": [
            { "functionalStationId": "1", "limit": 2700 },
            { "functionalStationId": "2", "limit": 2000 }
          ]
        },
        {
          "hour": 18,
          "functionalStation": [
            { "functionalStationId": "1", "limit": 2800 },
            { "functionalStationId": "2", "limit": 2000 }
          ]
        },
        {
          "hour": 19,
          "functionalStation": [
            { "functionalStationId": "1", "limit": 1900 },
            { "functionalStationId": "2", "limit": 2000 }
          ]
        },
        {
          "hour": 20,
          "functionalStation": [
            { "functionalStationId": "1", "limit": 3000 },
            { "functionalStationId": "2", "limit": 2000 }
          ]
        },
        {
          "hour": 21,
          "functionalStation": [
            { "functionalStationId": "1", "limit": 3100 },
            { "functionalStationId": "2", "limit": 2000 }
          ]
        },
        {
          "hour": 22,
          "functionalStation": [
            { "functionalStationId": "1", "limit": 3200 },
            { "functionalStationId": "2", "limit": 2000 }
          ]
        },
        {
          "hour": 23,
          "functionalStation": [
            { "functionalStationId": "1", "limit": 3300 },
            { "functionalStationId": "2", "limit": 2000 }
          ]
        }
      ]
    },
    {
      "id": 2,
      "name": "Monday",
      "limits": [
        {
          "hour": 0,
          "functionalStation": [
            { "functionalStationId": "1", "limit": 1000 },
            { "functionalStationId": "2", "limit": 2000 }
          ]
        },
        {
          "hour": 1,
          "functionalStation": [
            { "functionalStationId": "1", "limit": 1100 },
            { "functionalStationId": "2", "limit": 2000 }
          ]
        },
        {
          "hour": 2,
          "functionalStation": [
            { "functionalStationId": "1", "limit": 1200 },
            { "functionalStationId": "2", "limit": 2000 }
          ]
        },
        {
          "hour": 3,
          "functionalStation": [
            { "functionalStationId": "1", "limit": 1300 },
            { "functionalStationId": "2", "limit": 2000 }
          ]
        },
        {
          "hour": 4,
          "functionalStation": [
            { "functionalStationId": "1", "limit": 1400 },
            { "functionalStationId": "2", "limit": 2000 }
          ]
        },
        {
          "hour": 5,
          "functionalStation": [
            { "functionalStationId": "1", "limit": 1500 },
            { "functionalStationId": "2", "limit": 2000 }
          ]
        },
        {
          "hour": 6,
          "functionalStation": [
            { "functionalStationId": "1", "limit": 1600 },
            { "functionalStationId": "2", "limit": 2000 }
          ]
        },
        {
          "hour": 7,
          "functionalStation": [
            { "functionalStationId": "1", "limit": 1700 },
            { "functionalStationId": "2", "limit": 2000 }
          ]
        },
        {
          "hour": 8,
          "functionalStation": [
            { "functionalStationId": "1", "limit": 1800 },
            { "functionalStationId": "2", "limit": 2000 }
          ]
        },
        {
          "hour": 9,
          "functionalStation": [
            { "functionalStationId": "1", "limit": 1900 },
            { "functionalStationId": "2", "limit": 2000 }
          ]
        },
        {
          "hour": 10,
          "functionalStation": [
            { "functionalStationId": "1", "limit": 2000 },
            { "functionalStationId": "2", "limit": 2000 }
          ]
        },
        {
          "hour": 11,
          "functionalStation": [
            { "functionalStationId": "1", "limit": 1100 },
            { "functionalStationId": "2", "limit": 2000 }
          ]
        },
        {
          "hour": 12,
          "functionalStation": [
            { "functionalStationId": "1", "limit": 1200 },
            { "functionalStationId": "2", "limit": 2000 }
          ]
        },
        {
          "hour": 13,
          "functionalStation": [
            { "functionalStationId": "1", "limit": 1300 },
            { "functionalStationId": "2", "limit": 2000 }
          ]
        },
        {
          "hour": 14,
          "functionalStation": [
            { "functionalStationId": "1", "limit": 1400 },
            { "functionalStationId": "2", "limit": 2000 }
          ]
        },
        {
          "hour": 15,
          "functionalStation": [
            { "functionalStationId": "1", "limit": 1500 },
            { "functionalStationId": "2", "limit": 2000 }
          ]
        },
        {
          "hour": 16,
          "functionalStation": [
            { "functionalStationId": "1", "limit": 2600 },
            { "functionalStationId": "2", "limit": 2000 }
          ]
        },
        {
          "hour": 17,
          "functionalStation": [
            { "functionalStationId": "1", "limit": 2700 },
            { "functionalStationId": "2", "limit": 2000 }
          ]
        },
        {
          "hour": 18,
          "functionalStation": [
            { "functionalStationId": "1", "limit": 2800 },
            { "functionalStationId": "2", "limit": 2000 }
          ]
        },
        {
          "hour": 19,
          "functionalStation": [
            { "functionalStationId": "1", "limit": 1900 },
            { "functionalStationId": "2", "limit": 2000 }
          ]
        },
        {
          "hour": 20,
          "functionalStation": [
            { "functionalStationId": "1", "limit": 3000 },
            { "functionalStationId": "2", "limit": 2000 }
          ]
        },
        {
          "hour": 21,
          "functionalStation": [
            { "functionalStationId": "1", "limit": 3100 },
            { "functionalStationId": "2", "limit": 2000 }
          ]
        },
        {
          "hour": 22,
          "functionalStation": [
            { "functionalStationId": "1", "limit": 3200 },
            { "functionalStationId": "2", "limit": 2000 }
          ]
        },
        {
          "hour": 23,
          "functionalStation": [
            { "functionalStationId": "1", "limit": 3300 },
            { "functionalStationId": "2", "limit": 2000 }
          ]
        }
      ]
    },
    {
      "id": 4,
      "name": "Wednesday",
      "limits": [
        {
          "hour": 0,
          "functionalStation": [
            { "functionalStationId": "1", "limit": 1000 },
            { "functionalStationId": "2", "limit": 2000 }
          ]
        },
        {
          "hour": 1,
          "functionalStation": [
            { "functionalStationId": "1", "limit": 1100 },
            { "functionalStationId": "2", "limit": 2000 }
          ]
        },
        {
          "hour": 2,
          "functionalStation": [
            { "functionalStationId": "1", "limit": 1200 },
            { "functionalStationId": "2", "limit": 2000 }
          ]
        },
        {
          "hour": 3,
          "functionalStation": [
            { "functionalStationId": "1", "limit": 1300 },
            { "functionalStationId": "2", "limit": 2000 }
          ]
        },
        {
          "hour": 4,
          "functionalStation": [
            { "functionalStationId": "1", "limit": 1400 },
            { "functionalStationId": "2", "limit": 2000 }
          ]
        },
        {
          "hour": 5,
          "functionalStation": [
            { "functionalStationId": "1", "limit": 1500 },
            { "functionalStationId": "2", "limit": 2000 }
          ]
        },
        {
          "hour": 6,
          "functionalStation": [
            { "functionalStationId": "1", "limit": 1600 },
            { "functionalStationId": "2", "limit": 2000 }
          ]
        },
        {
          "hour": 7,
          "functionalStation": [
            { "functionalStationId": "1", "limit": 1700 },
            { "functionalStationId": "2", "limit": 2000 }
          ]
        },
        {
          "hour": 8,
          "functionalStation": [
            { "functionalStationId": "1", "limit": 1800 },
            { "functionalStationId": "2", "limit": 2000 }
          ]
        },
        {
          "hour": 9,
          "functionalStation": [
            { "functionalStationId": "1", "limit": 1900 },
            { "functionalStationId": "2", "limit": 2000 }
          ]
        },
        {
          "hour": 10,
          "functionalStation": [
            { "functionalStationId": "1", "limit": 2000 },
            { "functionalStationId": "2", "limit": 2000 }
          ]
        },
        {
          "hour": 11,
          "functionalStation": [
            { "functionalStationId": "1", "limit": 1100 },
            { "functionalStationId": "2", "limit": 2000 }
          ]
        },
        {
          "hour": 12,
          "functionalStation": [
            { "functionalStationId": "1", "limit": 1200 },
            { "functionalStationId": "2", "limit": 2000 }
          ]
        },
        {
          "hour": 13,
          "functionalStation": [
            { "functionalStationId": "1", "limit": 1300 },
            { "functionalStationId": "2", "limit": 2000 }
          ]
        },
        {
          "hour": 14,
          "functionalStation": [
            { "functionalStationId": "1", "limit": 500 },
            { "functionalStationId": "2", "limit": 600 }
          ]
        },
        {
          "hour": 15,
          "functionalStation": [
            { "functionalStationId": "1", "limit": 1500 },
            { "functionalStationId": "2", "limit": 2000 }
          ]
        },
        {
          "hour": 16,
          "functionalStation": [
            { "functionalStationId": "1", "limit": 2600 },
            { "functionalStationId": "2", "limit": 2000 }
          ]
        },
        {
          "hour": 17,
          "functionalStation": [
            { "functionalStationId": "1", "limit": 400 },
            { "functionalStationId": "2", "limit": 400 }
          ]
        },
        {
          "hour": 18,
          "functionalStation": [
            { "functionalStationId": "1", "limit": 2800 },
            { "functionalStationId": "2", "limit": 2000 }
          ]
        },
        {
          "hour": 19,
          "functionalStation": [
            { "functionalStationId": "1", "limit": 1900 },
            { "functionalStationId": "2", "limit": 2000 }
          ]
        },
        {
          "hour": 20,
          "functionalStation": [
            { "functionalStationId": "1", "limit": 3000 },
            { "functionalStationId": "2", "limit": 2000 }
          ]
        },
        {
          "hour": 21,
          "functionalStation": [
            { "functionalStationId": "1", "limit": 3100 },
            { "functionalStationId": "2", "limit": 2000 }
          ]
        },
        {
          "hour": 22,
          "functionalStation": [
            { "functionalStationId": "1", "limit": 3200 },
            { "functionalStationId": "2", "limit": 2000 }
          ]
        },
        {
          "hour": 23,
          "functionalStation": [
            { "functionalStationId": "1", "limit": 3300 },
            { "functionalStationId": "2", "limit": 2000 }
          ]
        }
      ]
    },
    {
      "id": 6,
      "name": "Friday",
      "limits": [
        {
          "hour": 0,
          "functionalStation": [
            { "functionalStationId": "1", "limit": 1000 },
            { "functionalStationId": "2", "limit": 2000 }
          ]
        },
        {
          "hour": 1,
          "functionalStation": [
            { "functionalStationId": "1", "limit": 1100 },
            { "functionalStationId": "2", "limit": 2000 }
          ]
        },
        {
          "hour": 2,
          "functionalStation": [
            { "functionalStationId": "1", "limit": 1200 },
            { "functionalStationId": "2", "limit": 2000 }
          ]
        },
        {
          "hour": 3,
          "functionalStation": [
            { "functionalStationId": "1", "limit": 1300 },
            { "functionalStationId": "2", "limit": 2000 }
          ]
        },
        {
          "hour": 4,
          "functionalStation": [
            { "functionalStationId": "1", "limit": 1400 },
            { "functionalStationId": "2", "limit": 2000 }
          ]
        },
        {
          "hour": 5,
          "functionalStation": [
            { "functionalStationId": "1", "limit": 1500 },
            { "functionalStationId": "2", "limit": 2000 }
          ]
        },
        {
          "hour": 6,
          "functionalStation": [
            { "functionalStationId": "1", "limit": 1600 },
            { "functionalStationId": "2", "limit": 2000 }
          ]
        },
        {
          "hour": 7,
          "functionalStation": [
            { "functionalStationId": "1", "limit": 1700 },
            { "functionalStationId": "2", "limit": 2000 }
          ]
        },
        {
          "hour": 8,
          "functionalStation": [
            { "functionalStationId": "1", "limit": 1800 },
            { "functionalStationId": "2", "limit": 2000 }
          ]
        },
        {
          "hour": 9,
          "functionalStation": [
            { "functionalStationId": "1", "limit": 1900 },
            { "functionalStationId": "2", "limit": 2000 }
          ]
        },
        {
          "hour": 10,
          "functionalStation": [
            { "functionalStationId": "1", "limit": 2000 },
            { "functionalStationId": "2", "limit": 2000 }
          ]
        },
        {
          "hour": 11,
          "functionalStation": [
            { "functionalStationId": "1", "limit": 1100 },
            { "functionalStationId": "2", "limit": 2000 }
          ]
        },
        {
          "hour": 12,
          "functionalStation": [
            { "functionalStationId": "1", "limit": 1200 },
            { "functionalStationId": "2", "limit": 2000 }
          ]
        },
        {
          "hour": 13,
          "functionalStation": [
            { "functionalStationId": "1", "limit": 1300 },
            { "functionalStationId": "2", "limit": 2000 }
          ]
        },
        {
          "hour": 14,
          "functionalStation": [
            { "functionalStationId": "1", "limit": 1400 },
            { "functionalStationId": "2", "limit": 2000 }
          ]
        },
        {
          "hour": 15,
          "functionalStation": [
            { "functionalStationId": "1", "limit": 1500 },
            { "functionalStationId": "2", "limit": 2000 }
          ]
        },
        {
          "hour": 16,
          "functionalStation": [
            { "functionalStationId": "1", "limit": 2600 },
            { "functionalStationId": "2", "limit": 2000 }
          ]
        },
        {
          "hour": 17,
          "functionalStation": [
            { "functionalStationId": "1", "limit": 2700 },
            { "functionalStationId": "2", "limit": 2000 }
          ]
        },
        {
          "hour": 18,
          "functionalStation": [
            { "functionalStationId": "1", "limit": 2800 },
            { "functionalStationId": "2", "limit": 2000 }
          ]
        },
        {
          "hour": 19,
          "functionalStation": [
            { "functionalStationId": "1", "limit": 1900 },
            { "functionalStationId": "2", "limit": 2000 }
          ]
        },
        {
          "hour": 20,
          "functionalStation": [
            { "functionalStationId": "1", "limit": 3000 },
            { "functionalStationId": "2", "limit": 2000 }
          ]
        },
        {
          "hour": 21,
          "functionalStation": [
            { "functionalStationId": "1", "limit": 3100 },
            { "functionalStationId": "2", "limit": 2000 }
          ]
        },
        {
          "hour": 22,
          "functionalStation": [
            { "functionalStationId": "1", "limit": 3200 },
            { "functionalStationId": "2", "limit": 2000 }
          ]
        },
        {
          "hour": 23,
          "functionalStation": [
            { "functionalStationId": "1", "limit": 3300 },
            { "functionalStationId": "2", "limit": 2000 }
          ]
        }
      ]
    },
    {
      "id": 1,
      "name": "Sunday",
      "limits": [
        {
          "hour": 0,
          "functionalStation": [
            { "functionalStationId": "1", "limit": 1000 },
            { "functionalStationId": "2", "limit": 2000 }
          ]
        },
        {
          "hour": 1,
          "functionalStation": [
            { "functionalStationId": "1", "limit": 1100 },
            { "functionalStationId": "2", "limit": 2000 }
          ]
        },
        {
          "hour": 2,
          "functionalStation": [
            { "functionalStationId": "1", "limit": 1200 },
            { "functionalStationId": "2", "limit": 2000 }
          ]
        },
        {
          "hour": 3,
          "functionalStation": [
            { "functionalStationId": "1", "limit": 1300 },
            { "functionalStationId": "2", "limit": 2000 }
          ]
        },
        {
          "hour": 4,
          "functionalStation": [
            { "functionalStationId": "1", "limit": 1400 },
            { "functionalStationId": "2", "limit": 2000 }
          ]
        },
        {
          "hour": 5,
          "functionalStation": [
            { "functionalStationId": "1", "limit": 1500 },
            { "functionalStationId": "2", "limit": 2000 }
          ]
        },
        {
          "hour": 6,
          "functionalStation": [
            { "functionalStationId": "1", "limit": 1600 },
            { "functionalStationId": "2", "limit": 2000 }
          ]
        },
        {
          "hour": 7,
          "functionalStation": [
            { "functionalStationId": "1", "limit": 1700 },
            { "functionalStationId": "2", "limit": 2000 }
          ]
        },
        {
          "hour": 8,
          "functionalStation": [
            { "functionalStationId": "1", "limit": 1800 },
            { "functionalStationId": "2", "limit": 2000 }
          ]
        },
        {
          "hour": 9,
          "functionalStation": [
            { "functionalStationId": "1", "limit": 1900 },
            { "functionalStationId": "2", "limit": 2000 }
          ]
        },
        {
          "hour": 10,
          "functionalStation": [
            { "functionalStationId": "1", "limit": 2000 },
            { "functionalStationId": "2", "limit": 2000 }
          ]
        },
        {
          "hour": 11,
          "functionalStation": [
            { "functionalStationId": "1", "limit": 1100 },
            { "functionalStationId": "2", "limit": 2000 }
          ]
        },
        {
          "hour": 12,
          "functionalStation": [
            { "functionalStationId": "1", "limit": 1200 },
            { "functionalStationId": "2", "limit": 2000 }
          ]
        },
        {
          "hour": 13,
          "functionalStation": [
            { "functionalStationId": "1", "limit": 1300 },
            { "functionalStationId": "2", "limit": 2000 }
          ]
        },
        {
          "hour": 14,
          "functionalStation": [
            { "functionalStationId": "1", "limit": 1400 },
            { "functionalStationId": "2", "limit": 2000 }
          ]
        },
        {
          "hour": 15,
          "functionalStation": [
            { "functionalStationId": "1", "limit": 1500 },
            { "functionalStationId": "2", "limit": 2000 }
          ]
        },
        {
          "hour": 16,
          "functionalStation": [
            { "functionalStationId": "1", "limit": 2600 },
            { "functionalStationId": "2", "limit": 2000 }
          ]
        },
        {
          "hour": 17,
          "functionalStation": [
            { "functionalStationId": "1", "limit": 2700 },
            { "functionalStationId": "2", "limit": 2000 }
          ]
        },
        {
          "hour": 18,
          "functionalStation": [
            { "functionalStationId": "1", "limit": 2800 },
            { "functionalStationId": "2", "limit": 2000 }
          ]
        },
        {
          "hour": 19,
          "functionalStation": [
            { "functionalStationId": "1", "limit": 1900 },
            { "functionalStationId": "2", "limit": 2000 }
          ]
        },
        {
          "hour": 20,
          "functionalStation": [
            { "functionalStationId": "1", "limit": 3000 },
            { "functionalStationId": "2", "limit": 2000 }
          ]
        },
        {
          "hour": 21,
          "functionalStation": [
            { "functionalStationId": "1", "limit": 3100 },
            { "functionalStationId": "2", "limit": 2000 }
          ]
        },
        {
          "hour": 22,
          "functionalStation": [
            { "functionalStationId": "1", "limit": 3200 },
            { "functionalStationId": "2", "limit": 2000 }
          ]
        },
        {
          "hour": 23,
          "functionalStation": [
            { "functionalStationId": "1", "limit": 3300 },
            { "functionalStationId": "2", "limit": 2000 }
          ]
        }
      ]
    },
    {
      "id": 5,
      "name": "Thursday",
      "limits": [
        {
          "hour": 0,
          "functionalStation": [
            { "functionalStationId": "1", "limit": 1000 },
            { "functionalStationId": "2", "limit": 2000 }
          ]
        },
        {
          "hour": 1,
          "functionalStation": [
            { "functionalStationId": "1", "limit": 1100 },
            { "functionalStationId": "2", "limit": 2000 }
          ]
        },
        {
          "hour": 2,
          "functionalStation": [
            { "functionalStationId": "1", "limit": 1200 },
            { "functionalStationId": "2", "limit": 2000 }
          ]
        },
        {
          "hour": 3,
          "functionalStation": [
            { "functionalStationId": "1", "limit": 1300 },
            { "functionalStationId": "2", "limit": 2000 }
          ]
        },
        {
          "hour": 4,
          "functionalStation": [
            { "functionalStationId": "1", "limit": 1400 },
            { "functionalStationId": "2", "limit": 2000 }
          ]
        },
        {
          "hour": 5,
          "functionalStation": [
            { "functionalStationId": "1", "limit": 1500 },
            { "functionalStationId": "2", "limit": 2000 }
          ]
        },
        {
          "hour": 6,
          "functionalStation": [
            { "functionalStationId": "1", "limit": 1600 },
            { "functionalStationId": "2", "limit": 2000 }
          ]
        },
        {
          "hour": 7,
          "functionalStation": [
            { "functionalStationId": "1", "limit": 1700 },
            { "functionalStationId": "2", "limit": 2000 }
          ]
        },
        {
          "hour": 8,
          "functionalStation": [
            { "functionalStationId": "1", "limit": 1800 },
            { "functionalStationId": "2", "limit": 2000 }
          ]
        },
        {
          "hour": 9,
          "functionalStation": [
            { "functionalStationId": "1", "limit": 1900 },
            { "functionalStationId": "2", "limit": 2000 }
          ]
        },
        {
          "hour": 10,
          "functionalStation": [
            { "functionalStationId": "1", "limit": 2000 },
            { "functionalStationId": "2", "limit": 2000 }
          ]
        },
        {
          "hour": 11,
          "functionalStation": [
            { "functionalStationId": "1", "limit": 1100 },
            { "functionalStationId": "2", "limit": 2000 }
          ]
        },
        {
          "hour": 12,
          "functionalStation": [
            { "functionalStationId": "1", "limit": 1200 },
            { "functionalStationId": "2", "limit": 2000 }
          ]
        },
        {
          "hour": 13,
          "functionalStation": [
            { "functionalStationId": "1", "limit": 1300 },
            { "functionalStationId": "2", "limit": 2000 }
          ]
        },
        {
          "hour": 14,
          "functionalStation": [
            { "functionalStationId": "1", "limit": 1400 },
            { "functionalStationId": "2", "limit": 2000 }
          ]
        },
        {
          "hour": 15,
          "functionalStation": [
            { "functionalStationId": "1", "limit": 1500 },
            { "functionalStationId": "2", "limit": 2000 }
          ]
        },
        {
          "hour": 16,
          "functionalStation": [
            { "functionalStationId": "1", "limit": 2600 },
            { "functionalStationId": "2", "limit": 2000 }
          ]
        },
        {
          "hour": 17,
          "functionalStation": [
            { "functionalStationId": "1", "limit": 2700 },
            { "functionalStationId": "2", "limit": 2000 }
          ]
        },
        {
          "hour": 18,
          "functionalStation": [
            { "functionalStationId": "1", "limit": 2800 },
            { "functionalStationId": "2", "limit": 2000 }
          ]
        },
        {
          "hour": 19,
          "functionalStation": [
            { "functionalStationId": "1", "limit": 1900 },
            { "functionalStationId": "2", "limit": 2000 }
          ]
        },
        {
          "hour": 20,
          "functionalStation": [
            { "functionalStationId": "1", "limit": 3000 },
            { "functionalStationId": "2", "limit": 2000 }
          ]
        },
        {
          "hour": 21,
          "functionalStation": [
            { "functionalStationId": "1", "limit": 3100 },
            { "functionalStationId": "2", "limit": 2000 }
          ]
        },
        {
          "hour": 22,
          "functionalStation": [
            { "functionalStationId": "1", "limit": 3200 },
            { "functionalStationId": "2", "limit": 2000 }
          ]
        },
        {
          "hour": 23,
          "functionalStation": [
            { "functionalStationId": "1", "limit": 3300 },
            { "functionalStationId": "2", "limit": 2000 }
          ]
        }
      ]
    }
  ]
}
